binance_sdk_alpha/__init__.py
binance_sdk_alpha/alpha.py
binance_sdk_alpha/metadata.py
binance_sdk_alpha/rest_api/__init__.py
binance_sdk_alpha/rest_api/api/__init__.py
binance_sdk_alpha/rest_api/api/market_data_api.py
binance_sdk_alpha/rest_api/models/__init__.py
binance_sdk_alpha/rest_api/models/aggregated_trades_response.py
binance_sdk_alpha/rest_api/models/aggregated_trades_response_data_inner.py
binance_sdk_alpha/rest_api/models/enums.py
binance_sdk_alpha/rest_api/models/get_exchange_info_response.py
binance_sdk_alpha/rest_api/models/get_exchange_info_response_data.py
binance_sdk_alpha/rest_api/models/get_exchange_info_response_data_assets_inner.py
binance_sdk_alpha/rest_api/models/get_exchange_info_response_data_symbols_inner.py
binance_sdk_alpha/rest_api/models/get_exchange_info_response_data_symbols_inner_filters_inner.py
binance_sdk_alpha/rest_api/models/klines_response.py
binance_sdk_alpha/rest_api/models/klines_response_data_item.py
binance_sdk_alpha/rest_api/models/klines_response_data_item_inner.py
binance_sdk_alpha/rest_api/models/ticker_response.py
binance_sdk_alpha/rest_api/models/ticker_response_data.py
binance_sdk_alpha/rest_api/models/token_list_response.py
binance_sdk_alpha/rest_api/models/token_list_response_data_inner.py
binance_sdk_alpha/rest_api/rest_api.py
binance_sdk_alpha-1.0.0.dist-info/METADATA
binance_sdk_alpha-1.0.0.dist-info/WHEEL
binance_sdk_alpha-1.0.0.dist-info/licenses/LICENCE
binance_sdk_alpha-1.0.0.dist-info/RECORD
